{
  "daily_metadata": {
    "hanja_sound": "자",
    "hanja_meaning": "아들",
    "hanja_char": "子",
    "hanja_level": "7급",
    "linked_subject": "국어, 사회"
  },
  "step_1_etymology": {
    "visual_title": "강보에 싸인 아이 — 아들 자(子)",
    "etymology_story": "'아들 자(子)'는 강보에 싸여 팔을 들고 있는 아이 모습이에요. 아들뿐 아니라 '자녀'나 '사람'을 뜻하기도 해요!"
  },
  "step_2_words": [
    {
      "word_korean": "자녀(子女)",
      "etymology_dissection": "아들 자(子)+여자 녀(女)",
      "easy_definition": "아들과 딸",
      "context_sentence": "자녀를 사랑으로 키워요."
    },
    {
      "word_korean": "제자(弟子)",
      "etymology_dissection": "아우 제(弟)+아들 자(子)",
      "easy_definition": "가르침을 받는 학생",
      "context_sentence": "선생님의 제자가 됐어요."
    },
    {
      "word_korean": "자식(子息)",
      "etymology_dissection": "아들 자(子)+숨쉴 식(息)",
      "easy_definition": "자녀",
      "context_sentence": "자식을 위해 부모는 헌신해요."
    },
    {
      "word_korean": "왕자(王子)",
      "etymology_dissection": "임금 왕(王)+아들 자(子)",
      "easy_definition": "왕의 아들",
      "context_sentence": "왕자가 용감하게 싸웠어요."
    }
  ],
  "step_3_reading_comprehension": {
    "passage_title": "자녀와 스승",
    "passage_text": "**자녀(子女)**는 부모의 가장 큰 선물이에요. **제자(弟子)**는 스승의 가르침을 이어받아요. **왕자(王子)** 같은 당당함을 갖춰요.",
    "quiz": {
      "question": "'제자(弟子)'란?",
      "choices": [
        "왕의 아들",
        "아들과 딸",
        "가르침을 받는 학생",
        "자녀"
      ],
      "correct_answer_index": 2,
      "detailed_explanation": "'제자(弟子)'=아우 제+아들 자, 스승에게 배우는 학생이에요!"
    }
  },
  "step_4_writing_challenge": {
    "mission_guideline": "나는 누구의 제자인지, 또 나는 누구에게 가르침을 줄 수 있는지 문장으로 써 보세요.",
    "model_example": "나는 부모님과 선생님의 제자이며, 동생에게는 좋은 길을 보여주는 자식이 되고 싶어요."
  },
  "step_5_vocal_review": {
    "cheer_message": "'아들 — 자(子)! 아들 — 자(子)!' 열 번 외쳐요!"
  }
}