{
  "daily_metadata": {
    "hanja_sound": "해",
    "hanja_meaning": "바다",
    "hanja_char": "海",
    "hanja_level": "7급",
    "linked_subject": "과학, 사회"
  },
  "step_1_etymology": {
    "visual_title": "물이 가득한 어두운 곳 — 바다 해(海)",
    "etymology_story": "'바다 해(海)'는 물(水)과 어두울 매(每)가 합쳐진 글자예요. 어둡고 깊은 물이 가득한 곳이 '바다(海)'예요!"
  },
  "step_2_words": [
    {
      "word_korean": "해수(海水)",
      "etymology_dissection": "바다 해(海)+물 수(水)",
      "easy_definition": "바다 물",
      "context_sentence": "해수욕을 즐겨요."
    },
    {
      "word_korean": "해외(海外)",
      "etymology_dissection": "바다 해(海)+밖 외(外)",
      "easy_definition": "바다 건너 다른 나라",
      "context_sentence": "해외여행이 꿈이에요."
    },
    {
      "word_korean": "해양(海洋)",
      "etymology_dissection": "바다 해(海)+큰바다 양(洋)",
      "easy_definition": "넓은 바다",
      "context_sentence": "해양 생물이 다양해요."
    },
    {
      "word_korean": "항해(航海)",
      "etymology_dissection": "배 항(航)+바다 해(海)",
      "easy_definition": "배를 타고 바다를 가는 것",
      "context_sentence": "항해사가 꿈이에요."
    }
  ],
  "step_3_reading_comprehension": {
    "passage_title": "바다의 세계",
    "passage_text": "**해양(海洋)**은 지구의 70%를 차지해요. **항해(航海)**하듯 도전하는 삶이 멋져요. **해외(海外)**는 바다 너머 넓은 세계예요.",
    "quiz": {
      "question": "'항해(航海)'란?",
      "choices": [
        "바다 물",
        "바다 건너 다른 나라",
        "배를 타고 바다를 가는 것",
        "해양"
      ],
      "correct_answer_index": 2,
      "detailed_explanation": "'항해(航海)'=배 항+바다 해, 배를 타고 바다를 항해하는 것이에요!"
    }
  },
  "step_4_writing_challenge": {
    "mission_guideline": "바다나 해외에 대한 꿈을 문장으로 써 보세요.",
    "model_example": "드넓은 해양을 항해하며 해외의 넓은 세계를 탐험하는 것이 나의 꿈이에요."
  },
  "step_5_vocal_review": {
    "cheer_message": "'바다 — 해(海)! 바다 — 해(海)!' 열 번 외쳐요!"
  }
}